gotran/__init__.py
gotran/__main__.py
gotran/algorithms/__init__.py
gotran/algorithms/symbolicnewtonsolution.py
gotran/codegeneration/__init__.py
gotran/codegeneration/algorithmcomponents.py
gotran/codegeneration/avoidsympycontractions.py
gotran/codegeneration/codecomponent.py
gotran/codegeneration/codegenerators.py
gotran/codegeneration/compilemodule.py
gotran/codegeneration/latexcodegenerator.py
gotran/codegeneration/oderepresentation.py
gotran/codegeneration/solvercomponents.py
gotran/common/__init__.py
gotran/common/dicts.py
gotran/common/disk.py
gotran/common/options.py
gotran/input/__init__.py
gotran/input/cellml.py
gotran/input/mathml.py
gotran/model/__init__.py
gotran/model/expressions.py
gotran/model/loadmodel.py
gotran/model/ode.py
gotran/model/odecomponent.py
gotran/model/odeobjects.py
gotran/model/utils.py
gotran/scripts/__init__.py
gotran/scripts/cellml2gotran.py
gotran/scripts/gotran2c.py
gotran/scripts/gotran2cpp.py
gotran/scripts/gotran2cuda.py
gotran/scripts/gotran2dolfin.py
gotran/scripts/gotran2julia.py
gotran/scripts/gotran2latex.py
gotran/scripts/gotran2matlab.py
gotran/scripts/gotran2md.py
gotran/scripts/gotran2opencl.py
gotran/scripts/gotran2py.py
gotran/scripts/gotranexport.py
gotran/scripts/gotranprobe.py
gotran/scripts/gotranrun.py
gotran-2023.1.0.dist-info/LICENSE
gotran-2023.1.0.dist-info/METADATA
gotran-2023.1.0.dist-info/WHEEL
gotran-2023.1.0.dist-info/entry_points.txt
gotran-2023.1.0.dist-info/top_level.txt
gotran-2023.1.0.dist-info/RECORD
